{"name": {"null": "devRantron"}, "format": 1, "abstract": {"null": "An open source cross platform desktop application for devRant"}, "release": {"date": "Mon, 25 Jun 2018 23:53:21 GMT"}, "file": {"url": "https://github.com/tahnik/devRantron/releases/download/v1.5.2/devrantron-1.5.2-x86_64.AppImage", "size": 62368429, "type": 2, "architecture": "x86-64", "sha512checksum": "c5196062256047dbab0bbd857006b23b65b53444b42db55565361f7754c963ba5c0435b6a7d1884e1aba9b08f1c5edabdd73733e9e5c4ef1c6dad2e1cee30c9b"}, "keywords": [], "id": "devrantron.desktop", "categories": ["Development"]}