{
    "abstract": {
        "null": "Unofficial WhatsApp app"
    },
    "file": {
        "architecture": "x86-64",
        "sha512checksum": "a9ab4e4006ea5c26d66d78db77c190d32796b89cc9443a7add2ef0abdf67eefccc73c0e85715d58ad4e82b2e02fdb8900f8371aa1c0a485bccfe0b44e3e9d38b",
        "size": 45678592,
        "type": 1,
        "url": "https://github.com/mawie81/whatsdesktop/releases/download/1.8.0/whatsdesktop-1.8.0-x86_64.AppImage"
    },
    "format": 1,
    "id": "whatsdesktop.desktop",
    "keywords": [],
    "name": {
        "null": "WhatsDesktop"
    },
    "release": {
        "date": "b'Wed, 18 Jul 2018 05:08:33 GMT'"
    }
}