{
    "abstract": {
        "null": "Rebaslight - an easy to use special effects editor"
    },
    "categories": [
        "Graphics"
    ],
    "file": {
        "architecture": "x86-64",
        "sha512checksum": "62c3f0180f9265a983f924275c7d81fd0e06bab3c3bff2f50441ed0bfd38882574c7f863f46baa9c6ef3bc794482095a44ff91c8c260b03c8d5af9f4adf74ef3",
        "size": 66139939,
        "type": 2,
        "url": "https://github.com/rebaslight/rebaslight/releases/download/v3.4.1/rebaslight-3.4.1-x86_64.AppImage"
    },
    "format": 1,
    "id": "rebaslight.desktop",
    "keywords": [],
    "name": {
        "null": "Rebaslight"
    },
    "release": {
        "date": "b'Wed, 18 Jul 2018 03:37:40 GMT'"
    }
}