{
    "abstract": {
        "null": "Development tool for the Microsoft Bot Framework. Allows developers to test and debug bots on localhost."
    },
    "categories": [
        "Development"
    ],
    "file": {
        "architecture": "Intel 80386",
        "sha512checksum": "74a478c3173c00b004e4fb276910bf20afa235625250d610b922234c7aea082c895ad6308277189c44b895facb5d264d03ded7b7fd6daff5f7f9d6e7ca162323",
        "size": 96790356,
        "type": 2,
        "url": "https://github.com/Microsoft/BotFramework-Emulator/releases/download/v4.0.15-alpha/botframework-emulator-4.0.15-alpha-i386.AppImage"
    },
    "format": 1,
    "id": "botframework-emulator.desktop",
    "keywords": [],
    "name": {
        "null": "Bot Framework Emulator"
    },
    "release": {
        "date": "b'Tue, 17 Jul 2018 23:02:33 GMT'"
    }
}