{
    "abstract": {
        "null": "Agent is the configuration application of the Ultimate Hacking Keyboard."
    },
    "categories": [
        "Utility"
    ],
    "file": {
        "architecture": "x86-64",
        "sha512checksum": "718780083cff5790e59132c1a776b1379f2c3e14b61b084f78630f0609b79012e9b60f6e238cb9accd8b740a41313583828ee4f0f8fc5547a192551bcd129d3a",
        "size": 54191324,
        "type": 2,
        "url": "https://github.com/UltimateHackingKeyboard/agent/releases/download/v1.2.2/UHK.Agent-1.2.2-linux-x86_64.AppImage"
    },
    "format": 1,
    "id": "uhk-agent.desktop",
    "keywords": [],
    "name": {
        "null": "UHK Agent"
    },
    "release": {
        "date": "b'Wed, 18 Jul 2018 04:53:43 GMT'"
    }
}