{
    "abstract": {
        "null": "An app for managing ROMs in Steam"
    },
    "categories": [
        "Utility"
    ],
    "file": {
        "architecture": "x86-64",
        "sha512checksum": "c88d14f5c37ce9c056504f12be69eb6f7582088e3d9444798b5bccf1e3493e4a1e797c86b9cf5635b54ce8d60534bf97d12e517d1fc0a14a3beef9311ee76110",
        "size": 61731264,
        "type": 2,
        "url": "https://github.com/FrogTheFrog/steam-rom-manager/releases/download/v2.2.14/steam-rom-manager-2.2.14-x86_64.AppImage"
    },
    "format": 1,
    "id": "steam-rom-manager.desktop",
    "keywords": [],
    "name": {
        "null": "Steam ROM Manager"
    },
    "release": {
        "date": "b'Wed, 18 Jul 2018 04:13:54 GMT'"
    }
}