{
    "abstract": {
        "null": "An app for managing ROMs in Steam"
    },
    "categories": [
        "Utility"
    ],
    "file": {
        "architecture": "x86-64",
        "sha512checksum": "3d622a10cc11ea970f148a2fac682395d73d18881cb40afd0ae3cc157a66b82cbd9065cd7323afdd85a85b8acd490d2013c5f25d73d4caceb216a7836b8665a9",
        "size": 61731470,
        "type": 2,
        "url": "https://github.com/FrogTheFrog/steam-rom-manager/releases/download/v2.2.15/steam-rom-manager-2.2.15-x86_64.AppImage"
    },
    "format": 1,
    "id": "steam-rom-manager.desktop",
    "keywords": [],
    "name": {
        "null": "Steam ROM Manager"
    },
    "release": {
        "date": "b'Wed, 18 Jul 2018 04:13:54 GMT'"
    }
}