{
    "abstract": {
        "null": "A new age editor for academics who seek freedom and people with cryptography needs in rich text environments."
    },
    "categories": [
        "Science"
    ],
    "file": {
        "architecture": "x86-64",
        "sha512checksum": "a49d83079d8ed7e4b8003bca3b65bb740c0c9a1aa7b4b774ce87268e807d780491fd9fad90faa6ec9c66f7bb4d5eac45f7d52f0f6c869e5e83c39e49bbc8d76a",
        "size": 59299788,
        "type": 2,
        "url": "https://github.com/fetacore/Infinitex/releases/download/v0.9.6/InfiniTex-0.9.6-x86_64.AppImage"
    },
    "format": 1,
    "id": "infinitex.desktop",
    "keywords": [],
    "name": {
        "null": "InfiniTex"
    },
    "release": {
        "date": "b'Wed, 18 Jul 2018 01:04:25 GMT'"
    }
}