{
    "abstract": {
        "null": "Desktop Client to assist with playing your damn turns."
    },
    "categories": [
        "StrategyGame"
    ],
    "file": {
        "architecture": "x86-64",
        "sha512checksum": "ce6f7facbc0c30ad578635b810a166829b1d610d3119857fa3eb4acc1f6aac4cf5752c2a423a817982d22e5c6f74a163f81477b140d18d306c7703627bb3f2ed",
        "size": 55261410,
        "type": 2,
        "url": "https://github.com/pydt/client/releases/download/v1.2.5/playyourdamnturn-1.2.5-x86_64.AppImage"
    },
    "format": 1,
    "id": "playyourdamnturn.desktop",
    "keywords": [],
    "name": {
        "null": "Play Your Damn Turn Client"
    },
    "release": {
        "date": "b'Wed, 18 Jul 2018 03:09:23 GMT'"
    }
}