{"name": {"null": "ArcadeManager"}, "format": 1, "abstract": {"null": "Arcade games manager to be used with Retropie and Recalbox"}, "release": {"date": "Mon, 25 Jun 2018 20:24:34 GMT"}, "file": {"url": "https://github.com/cosmo0/arcade-manager/releases/download/v4.0/ArcadeManager-4.0.0-linux.AppImage", "size": 51234915, "type": 2, "architecture": "x86-64", "sha512checksum": "6fd2b2b7ab9a600a269711690b31327b4d7c9172f123f7bb325e2d0dd5a63aece6c2b39778cba40ee2a30d1272ba551649495a8ad35fec294ce3bb87bf03655c"}, "keywords": [], "id": "arcade-manager.desktop", "categories": ["Game"]}