{
    "abstract": {
        "null": "IOTA Wallet GUI"
    },
    "file": {
        "architecture": "x86-64",
        "sha512checksum": "e2d16be273112997e17d3ccdab89df30d1a6c5f3b4788398d0178daf0d033fb03a199c479cb89787a8d1e035ae4a42bd38db4f3a7e253be3989fdac37b3111e0",
        "size": 44171264,
        "type": 1,
        "url": "https://github.com/iotaledger/iota-gui-beta/releases/download/0.9.25-zeta/IOTA.Wallet-0.9.25-zeta.AppImage"
    },
    "format": 1,
    "id": "iota.desktop",
    "keywords": [],
    "name": {
        "null": "IOTA Wallet"
    },
    "release": {
        "date": "b'Wed, 18 Jul 2018 01:08:05 GMT'"
    }
}